toolkit/__init__.py
toolkit/database/__init__.py
toolkit/database/firebase/__init__.py
toolkit/database/firebase/firebase.py
toolkit/database/json/__init__.py
toolkit/database/json/collectionDB.py
toolkit/database/mongodb/__init__.py
toolkit/database/mongodb/mongo_api.py
toolkit/database/mongodb/mongo_dao.py
toolkit/networking/__init__.py
toolkit/networking/address.py
toolkit/protocols/__init__.py
toolkit/protocols/mqtt.py
toolkit/utils/__init__.py
toolkit/utils/backup_utils.py
toolkit/utils/converter_utils.py
toolkit/utils/dataset_utils.py
toolkit/utils/date_utils.py
toolkit/utils/dict_utils.py
toolkit/utils/document_utils.py
toolkit/utils/io_utils.py
toolkit/utils/string_utils.py
python_toolkit_vald3nir-1.3.4.dist-info/METADATA
python_toolkit_vald3nir-1.3.4.dist-info/WHEEL
python_toolkit_vald3nir-1.3.4.dist-info/licenses/LICENSE
python_toolkit_vald3nir-1.3.4.dist-info/RECORD
